{
  "id": 47,
  "url": "https://academy.creatio.com/docs/8.x/dev/development-on-creatio-platform/integrations-and-api/chat-channels-integration",
  "title": "Integrate chat channels | Creatio Academy",
  "category": "development",
  "content": "Version: 8.3 On this page Level: intermediate Chats let your company's contact center agents process messages from popular chat messengers in Creatio. Learn more: Set up chat processing (user documentation). A chat channel is a source from which Creatio receives customer messages. Creatio lets you integrate the following chat channels : Facebook Messenger Telegram WhatsApp Ada AI chatbot Integrate a Facebook Messenger channel ​ Before you start the integration, take the following steps: Make sure Creatio cloud services are available . Make sure Facebook services are available . Learn more: Set up Facebook Messenger integration (user documentation). Creatio interacts with Facebook pages on behalf of the Creatio Social app that accesses the cloud services. The following actions are performed on the cloud service level: Subscribe to new incoming messages from the Facebook page. Bind the subscription to the Creatio instance. After the Facebook page receives an incoming message , Creatio cloud services forward it to the Creatio client. If the Creatio instance is unavailable, the services queue the message to resend it later. The Creatio instance sends outgoing messages directly without using the cloud services. View the interaction diagram of Creatio on-site and a Facebook Messenger channel in the figure below. Integrate a Telegram channel ​ Before you start the integration, take the following steps: Create an API for each Telegram chatbot . Specify the API in Creatio settings . Creatio does not use proxy services for Telegram integration. Learn more: Set up Telegram integration (user documentation). The Creatio instance receives an incoming message using long polling. Learn more: Long polling (Wikipedia). The instance sends repeated requests to Telegram API to check for new messages. View the template string for Telegram API requests below. Template string for Telegram API requests https://api.telegram.org/bot{token}/getUpdates Where token is the token you used to register the channel. The Creatio instance sends outgoing messages directly to Telegram service URLs. View the interaction diagram of Creatio on-site and a Telegram channel in the figure below. Integrate a WhatsApp channel ​ Before you start the integration, take the following steps: Make sure Creatio cloud services are available . Sign up for Twilio . Purchase a Twilio phone number to send and receive messages. Learn more: Set up WhatsApp integration (user documentation). After the Twilio phone number receives an incoming message , Creatio cloud services forward it to the Creatio client. If the Creatio instance is unavailable, the services queue the message to resend it later. The Creatio instance sends outgoing messages directly without using the cloud services. View the interaction diagram of Creatio on-site and a WhatsApp channel in the figure below. Integrate an Ada chat channel ​ Ada AI Chatbot app lets you integrate Ada AI-powered bots with chat processing on the user level as well as with Knowledge Management app. Learn more: Set up Ada AI chatbot (user documentation). Before you start the integration, take the following steps: Make sure Creatio cloud services are available . Sign up on the official Ada website . Purchase an Ada account and API Access Token to send and receive messages. Creatio interacts with Ada account on behalf of the Creatio webhook service that accesses the cloud services. Learn more: Webhook service integration (user documentation). After the Ada bot receives an incoming message , Creatio cloud services forward it to the Creatio client. If the Creatio instance is unavailable, the services queue the message to resend it later. The Creatio instance sends outgoing messages directly without using the cloud services. View the interaction diagram of Creatio on-site and an Ada chat channel in the figure below. See also ​ Set up chat processing (user documentation) Set up Facebook Messenger integration (user documentation) Set up Telegram integration (user documentation) Set up WhatsApp integration (user documentation) Set up Ada AI chatbot (user documentation) Webhook service integration (user documentation) Resources ​ Long polling (Wikipedia) Official Ada website Integrate a Facebook Messenger channel Integrate a Telegram channel Integrate a WhatsApp channel Integrate an Ada chat channel See also Resources",
  "markdown": "Integrate chat channels | Creatio Academy\n\nSkip to main content\n\n  * [Creatio](https://www.creatio.com/)\n  * [Community](https://community.creatio.com/)\n  * [Marketplace](https://marketplace.creatio.com/)\n  * [Knowledge Hub](https://knowledge-hub.creatio.com/)\n\n\n\nVersion: 8.3\n\nOn this page\n\nLevel: intermediate\n\nChats let your company's contact center agents process messages from popular chat messengers in Creatio. Learn more: [Set up chat processing](https://academy.creatio.com/documents?ver=8.3&id=2382) (user documentation).\n\nA **chat channel** is a source from which Creatio receives customer messages.\n\nCreatio lets you integrate the following **chat channels** :\n\n  * Facebook Messenger\n  * Telegram\n  * WhatsApp\n  * Ada AI chatbot\n\n\n\n## Integrate a Facebook Messenger channel​\n\nBefore you start the integration, take the following steps:\n\n  1. **Make sure Creatio cloud services are available**.\n  2. **Make sure Facebook services are available**.\n\n\n\nLearn more: [Set up Facebook Messenger integration](https://academy.creatio.com/documents?ver=8.3&id=2384) (user documentation).\n\nCreatio interacts with Facebook pages on behalf of the Creatio Social app that accesses the cloud services. The following actions are performed on the cloud service level:\n\n  * Subscribe to new incoming messages from the Facebook page.\n  * Bind the subscription to the Creatio instance.\n\n\n\nAfter the **Facebook page receives an incoming message** , Creatio cloud services forward it to the Creatio client. If the Creatio instance is unavailable, the services queue the message to resend it later.\n\nThe **Creatio instance sends outgoing messages** directly without using the cloud services.\n\nView the interaction diagram of Creatio on-site and a Facebook Messenger channel in the figure below.\n\n![](https://d3a7ykdi65m4cy.cloudfront.net/ac-en/s3fs-public/documentation/sdk/en/BPMonlineWebSDK/Screenshots/ChatChannels/8.1/scr_FacebookMessenger.png)\n\n## Integrate a Telegram channel​\n\nBefore you start the integration, take the following steps:\n\n  1. **Create an API for each Telegram chatbot**.\n  2. **Specify the API in Creatio settings**.\n\n\n\nCreatio does not use proxy services for Telegram integration. Learn more: [Set up Telegram integration](https://academy.creatio.com/documents?ver=8.3&id=2354) (user documentation).\n\nThe **Creatio instance receives an incoming message** using long polling. Learn more: [Long polling](https://en.wikipedia.org/w/index.php?title=Push_technology&oldid=1052758691#Long_polling) (Wikipedia). The instance sends repeated requests to Telegram API to check for new messages. View the template string for Telegram API requests below.\n\nTemplate string for Telegram API requests\n    \n    \n    https://api.telegram.org/bot{token}/getUpdates  \n    \n\nWhere `token` is the token you used to register the channel.\n\nThe **Creatio instance sends outgoing messages** directly to Telegram service URLs.\n\nView the interaction diagram of Creatio on-site and a Telegram channel in the figure below.\n\n![](https://d3a7ykdi65m4cy.cloudfront.net/ac-en/s3fs-public/documentation/sdk/en/BPMonlineWebSDK/Screenshots/ChatChannels/8.1/scr_Telegram.png)\n\n## Integrate a WhatsApp channel​\n\nBefore you start the integration, take the following steps:\n\n  1. **Make sure Creatio cloud services are available**.\n  2. **Sign up for Twilio**.\n  3. **Purchase a Twilio phone number** to send and receive messages.\n\n\n\nLearn more: [Set up WhatsApp integration](https://academy.creatio.com/documents?ver=8.3&id=2355) (user documentation).\n\nAfter the **Twilio phone number receives an incoming message** , Creatio cloud services forward it to the Creatio client. If the Creatio instance is unavailable, the services queue the message to resend it later.\n\nThe **Creatio instance sends outgoing messages** directly without using the cloud services.\n\nView the interaction diagram of Creatio on-site and a WhatsApp channel in the figure below.\n\n![](https://d3a7ykdi65m4cy.cloudfront.net/ac-en/s3fs-public/documentation/sdk/en/BPMonlineWebSDK/Screenshots/ChatChannels/8.1/scr_WhatsApp.png)\n\n## Integrate an Ada chat channel​\n\n**Ada AI Chatbot** app lets you integrate Ada AI-powered bots with chat processing on the user level as well as with **Knowledge Management** app. Learn more: [Set up Ada AI chatbot](https://academy.creatio.com/documents?ver=8.3&id=2531) (user documentation).\n\nBefore you start the integration, take the following steps:\n\n  1. **Make sure Creatio cloud services are available**.\n  2. **Sign up on the** [official Ada website](https://www.ada.cx/).\n  3. **Purchase an Ada account and API Access Token** to send and receive messages.\n\n\n\nCreatio interacts with Ada account on behalf of the Creatio webhook service that accesses the cloud services. Learn more: [Webhook service integration](https://academy.creatio.com/docs/8.x/no-code-customization/category/webhook-service-integration) (user documentation).\n\nAfter the **Ada bot receives an incoming message** , Creatio cloud services forward it to the Creatio client. If the Creatio instance is unavailable, the services queue the message to resend it later.\n\nThe **Creatio instance sends outgoing messages** directly without using the cloud services.\n\nView the interaction diagram of Creatio on-site and an Ada chat channel in the figure below.\n\n![](https://d3a7ykdi65m4cy.cloudfront.net/ac-en/s3fs-public/documentation/sdk/en/BPMonlineWebSDK/Screenshots/ChatChannels/8.1/scr_AdaAIChatbot.png)\n\n* * *\n\n## See also​\n\n[Set up chat processing](https://academy.creatio.com/documents?ver=8.3&id=2382) (user documentation)\n\n[Set up Facebook Messenger integration](https://academy.creatio.com/documents?ver=8.3&id=2384) (user documentation)\n\n[Set up Telegram integration](https://academy.creatio.com/documents?ver=8.3&id=2354) (user documentation)\n\n[Set up WhatsApp integration](https://academy.creatio.com/documents?ver=8.3&id=2355) (user documentation)\n\n[Set up Ada AI chatbot](https://academy.creatio.com/documents?ver=8.3&id=2531) (user documentation)\n\n[Webhook service integration](https://academy.creatio.com/docs/8.x/no-code-customization/category/webhook-service-integration) (user documentation)\n\n* * *\n\n## Resources​\n\n[Long polling](https://en.wikipedia.org/w/index.php?title=Push_technology&oldid=1052758691#Long_polling) (Wikipedia)\n\n[Official Ada website](https://www.ada.cx/)\n\n  * Integrate a Facebook Messenger channel\n  * Integrate a Telegram channel\n  * Integrate a WhatsApp channel\n  * Integrate an Ada chat channel\n  * See also\n  * Resources\n\n\n",
  "word_count": 665,
  "processed_at": "2025-07-28T12:59:36.630222"
}
