{
  "id": 681,
  "url": "https://academy.creatio.com/docs/8.x/creatio-apps/8.0/platform-basics/user-interface/creatio-interface",
  "title": "Get started with Creatio Classic UI | Creatio Academy",
  "category": "administration",
  "description": "Creatio UI (Fig. 1) consists of the side panel, communication panel, command line, folder and filter area, and the content of the page that is displayed currently.",
  "content": "This is documentation for Creatio 8.0 . For up-to-date documentation, see the latest version ( 8.3 ). Version: 8.0 All Creatio products On this page Creatio UI (Fig. 1) consists of the side panel, communication panel, command line, folder and filter area, and the content of the page that is displayed currently. Fig. 1 Creatio UI Side panel (1) ​ The side panel (or the section panel) is in the left and lets you navigate through the workplaces and sections. Also, the side panel contains quick access buttons for basic Creatio operations. Side panel buttons ​ is the main menu that contains the index of additional commands: Main menu opens the main Creatio page. The main page contains the index of Creatio sections as well as links to the System Designer and user profile page. Run process opens the process start window. note Learn more about the business process automation in the Creatio documentation on business processes. Collapse section panel / Expand section panel collapse or expand the side panel, respectively. Workplace displays the index of available workplaces. When you change a workplace, the index of sections available in the side panel also changes. You can edit the indexes of workplaces and sections within workplaces. User profile opens the user profile page that lets you view and edit personal Creatio settings. Exit ends the Creatio session. The command opens the login page. is the global process start button. If you did not set up any process for the button or the processes you set up are inactive, the button opens a window that contains the index of Creatio business processes. If at least one process you set up for the button is active, the button opens a menu that contains additional commands: Run process is the index of main business processes you can run. Another process opens a window that contains the index of Creatio business processes. note Set up the global process start button in the Process library section. Learn more in a separate article: Run a business process . opens the quick record add menu. Select the needed menu command to open a page that adds records to the corresponding section. note Set up the menu structure using the Quick add menu setup lookup. , collapses/expands the side panel. The collapsed panel displays action buttons and the icons of the current workplace's sections. The expanded panel displays action buttons, full section names, and the current workplace's name. Select a workplace ​ Switch between user workplaces using the menu on the side panel. You can select the needed workspace in the main menu of the collapsed (Fig. 2) or expanded (Fig. 3) side panel. Fig. 2 Select a workplace in the collapsed side panel Fig. 3 Select a workplace in the expanded side panel Communication panel (2) ​ Communication panel is in the right and lets you manage emails, make and receive calls, access Creatio user notifications quickly as well as view the feed of messages by other users. Command line (3) ​ Command line lets you search for and add records as well as execute other actions by entering text commands. Folder and filter area (4) ​ The area lets you apply advanced data filter settings and manage the section folder tree. Working area (5) ​ Depending on the section and selected view, the working area displays the following: the list of section records, for example, the contact list in the Contacts section the page of the open record the analytics tools of the current section special pages, for example, calendar in the Activities section Select a record in the list to open the toolbar (Fig. 4) that lets you open, copy, or delete the record. Click Run process to run a process for the record only. note Creatio displays the Run process button only if you set up a business process that runs for a section record. Fig. 4 List record toolbar See also ​ Work with record lists Work with mini pages Work with attachments Work with currencies Search records and run commands Resources ​ Creatio interface overview Side panel (1) Side panel buttons Select a workplace Communication panel (2) Command line (3) Folder and filter area (4) Working area (5) See also Resources",
  "markdown": "This is documentation for Creatio **8.0**.\n\nFor up-to-date documentation, see the **[latest version](/docs/8.x/creatio-apps/overview/platform-overview)** (8.3).\n\nVersion: 8.0All Creatio products\n\nOn this page\n\nCreatio UI (Fig. 1) consists of the side panel, communication panel, command line, folder and filter area, and the content of the page that is displayed currently.\n\nFig. 1 Creatio UI\n\n![Fig. 1 Creatio UI](https://academy.creatio.com/docs/sites/en/files/documentation/user/en/base/BPMonlineHelp/chapter_interface/scr_interface_workplace.png)\n\n## Side panel (1)​\n\nThe side panel (or the section panel) is in the left and lets you navigate through the workplaces and sections. Also, the side panel contains quick access buttons for basic Creatio operations.\n\n### Side panel buttons​\n\n![btn_com_main_menu.png](https://academy.creatio.com/guides/sites/en/files/documentation/user/en/base/BPMonlineHelp/chapter_interface/btn_com_main_menu.png) is the main menu that contains the index of additional commands:\n\n  * **Main menu** opens the main Creatio page. The main page contains the index of Creatio sections as well as links to the System Designer and user profile page.\n\n  * **Run process** opens the process start window.\n\n\n\n\nnote\n\nLearn more about the business process automation in the Creatio documentation on business processes.\n\n  * **Collapse section panel** / **Expand section panel** collapse or expand the side panel, respectively.\n\n  * **Workplace** displays the index of available workplaces. When you change a workplace, the index of sections available in the side panel also changes. [You can edit](https://academy.creatio.com/documents?id=1248) the indexes of workplaces and sections within workplaces.\n\n  * **User profile** opens the user profile page that lets you view and edit personal Creatio settings.\n\n  * **Exit** ends the Creatio session. The command opens the login page.\n\n\n\n\n![btn_com_sidebar_start_process.png](https://academy.creatio.com/guides/sites/en/files/documentation/user/en/base/BPMonlineHelp/chapter_interface/btn_com_sidebar_start_process.png) is the global process start button. If you did not set up any process for the button or the processes you set up are inactive, the button opens a window that contains the index of Creatio business processes. If at least one process you set up for the button is active, the button opens a menu that contains additional commands:\n\n  * **Run process** is the index of main business processes you can run.\n\n  * **Another process** opens a window that contains the index of Creatio business processes.\n\n\n\n\nnote\n\nSet up the global process start button in the **Process library** section. Learn more in a separate article: [Run a business process](https://academy.creatio.com/documents?id=7097#title-1884-3).\n\n![](https://academy.creatio.com/docs/sites/en/files/images/Platform_basics/get_started_with_creatio_ui/btn_com_action.png) opens the quick record add menu. Select the needed menu command to open a page that adds records to the corresponding section.\n\nnote\n\nSet up the menu structure using the **Quick add menu setup** lookup.\n\n![btn_com_minimize_menu.png](https://academy.creatio.com/guides/sites/en/files/documentation/user/en/base/BPMonlineHelp/chapter_interface/btn_com_minimize_menu.png), ![btn_com_maximize_menu.png](https://academy.creatio.com/guides/sites/en/files/documentation/user/en/base/BPMonlineHelp/chapter_interface/btn_com_maximize_menu.png) collapses/expands the side panel. The collapsed panel displays action buttons and the icons of the current workplace's sections. The expanded panel displays action buttons, full section names, and the current workplace's name.\n\n### Select a workplace​\n\nSwitch between user workplaces using the menu on the side panel. You can select the needed workspace in the main menu of the collapsed (Fig. 2) or expanded (Fig. 3) side panel.\n\nFig. 2 Select a workplace in the collapsed side panel\n\n![Fig. 2 Select a workplace in the collapsed side panel](https://academy.creatio.com/docs/sites/en/files/documentation/user/en/base/BPMonlineHelp/chapter_interface/scr_interface_select_workplace.png)\n\nFig. 3 Select a workplace in the expanded side panel\n\n![Fig. 3 Select a workplace in the expanded side panel](https://academy.creatio.com/docs/sites/en/files/documentation/user/en/base/BPMonlineHelp/chapter_interface/scr_interface_select_workplace_2.png)\n\n## Communication panel (2)​\n\n[Communication panel](https://academy.creatio.com/documents?id=1011) is in the right and lets you manage emails, make and receive calls, access Creatio user notifications quickly as well as view the feed of messages by other users.\n\n## Command line (3)​\n\n[Command line](https://academy.creatio.com/documents?id=1228) lets you search for and add records as well as execute other actions by entering text commands.\n\n## Folder and filter area (4)​\n\nThe area lets you apply advanced [data filter](https://academy.creatio.com/documents?id=1017) settings and manage the section [folder](https://academy.creatio.com/documents?id=1018) tree.\n\n## Working area (5)​\n\nDepending on the section and selected view, the working area displays the following:\n\n  * the [list](https://academy.creatio.com/documents?id=1016) of section records, for example, the contact list in the **Contacts** section\n  * the [page](https://academy.creatio.com/documents?id=1765) of the open record\n  * the [analytics tools](https://academy.creatio.com/documents?id=1837) of the current section\n  * special pages, for example, [calendar](https://academy.creatio.com/documents?id=1204) in the **Activities** section\n\n\n\nSelect a record in the list to open the toolbar (Fig. 4) that lets you open, copy, or delete the record. Click **Run process** to run a process for the record only.\n\nnote\n\nCreatio displays the **Run process** button only if you set up a business process that runs for a section record.\n\nFig. 4 List record toolbar\n\n![Fig. 4 List record toolbar](https://academy.creatio.com/docs/sites/en/files/documentation/user/en/base/BPMonlineHelp/chapter_interface/scr_interface_record_toolbar.png)\n\n* * *\n\n## See also​\n\n[Work with record lists](https://academy.creatio.com/documents?id=1016)\n\n[Work with mini pages](https://academy.creatio.com/documents?id=1622)\n\n[Work with attachments](https://academy.creatio.com/documents?id=1297)\n\n[Work with currencies](https://academy.creatio.com/documents?id=1584)\n\n[Search records and run commands](https://academy.creatio.com/documents?id=1228)\n\n* * *\n\n## Resources​\n\n[Creatio interface overview](https://academy.creatio.com/node/531087/takecourse)\n\n  * Side panel (1)\n    * Side panel buttons\n    * Select a workplace\n  * Communication panel (2)\n  * Command line (3)\n  * Folder and filter area (4)\n  * Working area (5)\n  * See also\n  * Resources\n\n\n",
  "analysis": {
    "word_count": 708,
    "key_concepts": ["business process", "section", "lookup", "operation", "notification", "contact", "automation"],
    "use_cases": [
      "building applications",
      "custom development",
      "API integration",
      "system administration",
      "user management"
    ],
    "related_topics": ["automation", "workflow", "process design", "bpm"],
    "difficulty": "beginner",
    "ai_tags": [
      "beginner",
      "creatio",
      "notification",
      "operation",
      "documentation",
      "section",
      "lookup",
      "business process"
    ]
  },
  "ai_optimized": true,
  "processed_at": "2025-07-28T13:28:10.902249"
}
